py_iochem/CMLtoPy.py
py_iochem/RESTAPIManager.py
py_iochem/RXioChem.py
py_iochem/__init__.py
uma_ase/__init__.py
uma_ase/__main__.py
uma_ase/cli.py
uma_ase/cml_export.py
uma_ase/md-uma.py
uma_ase/modes.py
uma_ase/server.py
uma_ase/styled_rmsd_report.py
uma_ase/utils.py
uma_ase/workflows.py
uma_ase/scripts-to-share_v2/driver.py
uma_ase/scripts-to-share_v2/plot_dist_angle_rmsd.py
uma_ase/scripts-to-share_v2/plot_worst_param.py
uma_ase/scripts-to-share_v2/rmsd.py
uma_ase/scripts-to-share_v2/rmsd_dist-angles_ranking_hetero-cutoff.py
uma_ase/static/.DS_Store
uma_ase/static/logo.svg
uma_ase/static/logoiciq.png
uma_ase/static/uma-ase.html
uma_ase/static/jsmol/.DS_Store
uma_ase/static/jsmol/JSmol.GLmol.min.js
uma_ase/static/jsmol/JSmol.lite.js
uma_ase/static/jsmol/JSmol.lite.nojq.js
uma_ase/static/jsmol/JSmol.min.js
uma_ase/static/jsmol/JSmol.min.js.0
uma_ase/static/jsmol/JSmol.min.nojq.js
uma_ase/static/jsmol/README.TXT
uma_ase/static/jsmol/img/JSmol_spinner 2.gif
uma_ase/static/jsmol/img/JSmol_spinner.gif
uma_ase/static/jsmol/j2s/Jmol.properties
uma_ase/static/jsmol/j2s/J/adapter/readers/.DS_Store
uma_ase/static/jsmol/j2s/J/adapter/readers/cif/BCIFDataParser.js
uma_ase/static/jsmol/j2s/J/adapter/readers/cif/BCIFDecoder.js
uma_ase/static/jsmol/j2s/J/adapter/readers/cif/BCIFReader.js
uma_ase/static/jsmol/j2s/J/adapter/readers/cif/Cif2DataParser.js
uma_ase/static/jsmol/j2s/J/adapter/readers/cif/Cif2Reader.js
uma_ase/static/jsmol/j2s/J/adapter/readers/cif/CifReader.js
uma_ase/static/jsmol/j2s/J/adapter/readers/cif/MMCifReader.js
uma_ase/static/jsmol/j2s/J/adapter/readers/cif/MMCifValidationParser.js
uma_ase/static/jsmol/j2s/J/adapter/readers/cif/MMTFReader.js
uma_ase/static/jsmol/j2s/J/adapter/readers/cif/MSCifParser.js
uma_ase/static/jsmol/j2s/J/adapter/readers/cif/MSRdr.js
uma_ase/static/jsmol/j2s/J/adapter/readers/cif/Subsystem.js
uma_ase/static/jsmol/j2s/J/adapter/readers/cif/TopoCifParser.js
uma_ase/static/jsmol/j2s/J/adapter/readers/molxyz/Mol3DReader.js
uma_ase-0.9.0.dist-info/licenses/LICENSE
uma_ase-0.9.0.dist-info/METADATA
uma_ase-0.9.0.dist-info/WHEEL
uma_ase-0.9.0.dist-info/entry_points.txt
uma_ase-0.9.0.dist-info/top_level.txt
uma_ase-0.9.0.dist-info/RECORD
