Metadata-Version: 2.4
Name: uma-ase
Version: 0.9.0
Summary: UMA machine-learned force-field integrated with ASE workflows
Author-email: "uma-ase Developers: ChatGPT_Codex+CBo_Group" <cbo@iciq.cat>
License:                     GNU GENERAL PUBLIC LICENSE
Project-URL: Homepage, https://gitlab.com/carlesbo/uma-ase
Project-URL: Repository, https://gitlab.com/carlesbo/uma-ase.git
Keywords: ase,uma,Fairchem,Meta/Facebook,computational chemistry,molecular-simulation,machine-learning,MLFF,thermochemistry
Classifier: License :: OSI Approved :: GNU General Public License v3 (GPLv3)
Classifier: Programming Language :: Python :: 3
Classifier: Operating System :: OS Independent
Classifier: Topic :: Scientific/Engineering :: Chemistry
Requires-Python: >=3.10
License-File: LICENSE
Requires-Dist: ase>=3.26.0
Requires-Dist: numpy>=2.2
Requires-Dist: torch>=2.6
Provides-Extra: server
Requires-Dist: flask>=3.0; extra == "server"
Dynamic: license-file
